This XML file does not appear to have any style information associated with it. The document tree is shown below.
<!--  Edited by XMLSpy®  -->
<pages>
<link>
<title>NBA home page</title>
<url>http://www.nba.com/</url>
</link>
<link>
<title>NBA 2017 playoffs</title>
<url>http://www.nba.com/playoffs/2017/index.html</url>
</link>
<link>
<title>Cleveland Cavaliers</title>
<url>http://www.nba.com/cavaliers/</url>
</link>
<link>
<title>Miami Heat</title>
<url>http://www.nba.com/heat/</url>
</link>
<link>
<title>Boston Celtics</title>
<url>http://www.nba.com/celtics/</url>
</link>
<link>
<title>Minnesota Timberwolves</title>
<url>http://www.nba.com/timberwolves</url>
</link>
<link>
<title>Jimmy Butler</title>
<url>http://www.nba.com/playerfile/jimmy_butler/</url>
</link>
<link>
<title>Kevin Love</title>
<url>http://www.nba.com/playerfile/kevin_love/</url>
</link>
<link>
<title>LeBron James</title>
<url>http://www.nba.com/playerfile/lebron_james/</url>
</link>
<link>
<title>Dwyane Wade</title>
<url>http://www.nba.com/playerfile/dwyane_wade/</url>
</link>
<link>
<title>Kevin Durant</title>
<url>http://www.nba.com/playerfile/kevin_durant/</url>
</link>
<link>
<title>Jeremy Lin</title>
<url>http://www.nba.com/playerfile/jeremy_lin/</url>
</link>
<link>
<title>Stephen Curry</title>
<url>http://www.nba.com/playerfile/stephen_curry/</url>
</link>
<link>
<title>Chicago Bulls</title>
<url>http://www.nba.com/bulls/</url>
</link>
<link>
<title>Golden State</title>
<url>http://www.nba.com/warriors/</url>
</link>
<link>
<title>San Antonio Spurs</title>
<url>http://www.nba.com/spurs/</url>
</link>
</pages>